{"records":[{"ts": 1583769658.4229164, "data": {"responseCode": "100", "responseText": "API input request executed successfully.", "sgID": 238421, "numStations": 5, "groupName": "Hilltop G GW", "sgLoad": "42.537", "stationData": [{"stationID": "1:195172", "stationName": "VMWARE / HILLTOP G3", "Address": "3421 Hillview Ave, Palo Alto, California,  94304, United States", "stationLoad": 8.848, "Port": [{"portNumber": "1", "userID": "58302", "credentialID": "bcf2194d8e9116", "shedState": 0, "portLoad": 6.009, "allowedLoad": 0.000, "percentShed": 0}, {"portNumber": "2", "userID": "98984", "credentialID": "ab69d23f732a03", "shedState": 0, "portLoad": 2.839, "allowedLoad": 0.000, "percentShed": 0}]}, {"stationID": "1:790778", "stationName": "VMWARE / HILLTOP G4", "Address": "3421 Hillview Ave, Palo Alto, California,  94304, United States", "stationLoad": 10.541, "Port": [{"portNumber": "1", "userID": "834871", "credentialID": "CNCP0000748973", "shedState": 0, "portLoad": 4.503, "allowedLoad": 0.000, "percentShed": 0}, {"portNumber": "2", "userID": "96268", "credentialID": "63f5606f4c1413", "shedState": 0, "portLoad": 6.038, "allowedLoad": 0.000, "percentShed": 0}]}, {"stationID": "1:101765", "stationName": "VMWARE / HILLTOP G5", "Address": "3421 Hillview Ave, Palo Alto, California,  94304, United States", "stationLoad": 11.602, "Port": [{"portNumber": "1", "userID": "10181", "credentialID": "8d5941e665c0e9", "shedState": 0, "portLoad": 5.729, "allowedLoad": 0.000, "percentShed": 0}, {"portNumber": "2", "userID": "80542", "credentialID": "e778ee763af38d", "shedState": 0, "portLoad": 5.872, "allowedLoad": 0.000, "percentShed": 0}]}, {"stationID": "1:594038", "stationName": "VMWARE / HILLTOP G1", "Address": "3421 Hillview Ave, Palo Alto, California,  94304, United States", "stationLoad": 0.000, "Port": [{"portNumber": "1", "userID": null, "credentialID": null, "shedState": 0, "portLoad": 0.000, "allowedLoad": 0.000, "percentShed": 0}]}, {"stationID": "1:461911", "stationName": "VMWARE / HILLTOP G2", "Address": "3421 Hillview Ave, Palo Alto, California,  94304, United States", "stationLoad": 11.546, "Port": [{"portNumber": "1", "userID": "91670", "credentialID": "43910817e0d5a3", "shedState": 0, "portLoad": 5.838, "allowedLoad": 0.000, "percentShed": 0}, {"portNumber": "2", "userID": "47708", "credentialID": "f5e61f45cd313f", "shedState": 0, "portLoad": 5.709, "allowedLoad": 0.000, "percentShed": 0}]}]}},{"ts": 1583769778.729706, "data": {"responseCode": "100", "responseText": "API input request executed successfully.", "sgID": 238421, "numStations": 5, "groupName": "Hilltop G GW", "sgLoad": "42.564", "stationData": [{"stationID": "1:195172", "stationName": "VMWARE / HILLTOP G3", "Address": "3421 Hillview Ave, Palo Alto, California,  94304, United States", "stationLoad": 8.848, "Port": [{"portNumber": "1", "userID": "58302", "credentialID": "bcf2194d8e9116", "shedState": 0, "portLoad": 6.009, "allowedLoad": 0.000, "percentShed": 0}, {"portNumber": "2", "userID": "98984", "credentialID": "ab69d23f732a03", "shedState": 0, "portLoad": 2.839, "allowedLoad": 0.000, "percentShed": 0}]}, {"stationID": "1:790778", "stationName": "VMWARE / HILLTOP G4", "Address": "3421 Hillview Ave, Palo Alto, California,  94304, United States", "stationLoad": 10.569, "Port": [{"portNumber": "1", "userID": "834871", "credentialID": "CNCP0000748973", "shedState": 0, "portLoad": 4.519, "allowedLoad": 0.000, "percentShed": 0}, {"portNumber": "2", "userID": "96268", "credentialID": "63f5606f4c1413", "shedState": 0, "portLoad": 6.049, "allowedLoad": 0.000, "percentShed": 0}]}, {"stationID": "1:101765", "stationName": "VMWARE / HILLTOP G5", "Address": "3421 Hillview Ave, Palo Alto, California,  94304, United States", "stationLoad": 11.602, "Port": [{"portNumber": "1", "userID": "10181", "credentialID": "8d5941e665c0e9", "shedState": 0, "portLoad": 5.729, "allowedLoad": 0.000, "percentShed": 0}, {"portNumber": "2", "userID": "80542", "credentialID": "e778ee763af38d", "shedState": 0, "portLoad": 5.872, "allowedLoad": 0.000, "percentShed": 0}]}, {"stationID": "1:594038", "stationName": "VMWARE / HILLTOP G1", "Address": "3421 Hillview Ave, Palo Alto, California,  94304, United States", "stationLoad": 0.000, "Port": [{"portNumber": "1", "userID": null, "credentialID": null, "shedState": 0, "portLoad": 0.000, "allowedLoad": 0.000, "percentShed": 0}]}, {"stationID": "1:461911", "stationName": "VMWARE / HILLTOP G2", "Address": "3421 Hillview Ave, Palo Alto, California,  94304, United States", "stationLoad": 11.546, "Port": [{"portNumber": "1", "userID": "91670", "credentialID": "43910817e0d5a3", "shedState": 0, "portLoad": 5.838, "allowedLoad": 0.000, "percentShed": 0}, {"portNumber": "2", "userID": "47708", "credentialID": "f5e61f45cd313f", "shedState": 0, "portLoad": 5.709, "allowedLoad": 0.000, "percentShed": 0}]}]}},{"ts": 1583769899.1234848, "data": {"responseCode": "100", "responseText": "API input request executed successfully.", "sgID": 238421, "numStations": 5, "groupName": "Hilltop G GW", "sgLoad": "39.830", "stationData": [{"stationID": "1:195172", "stationName": "VMWARE / HILLTOP G3", "Address": "3421 Hillview Ave, Palo Alto, California,  94304, United States", "stationLoad": 6.021, "Port": [{"portNumber": "1", "userID": "58302", "credentialID": "bcf2194d8e9116", "shedState": 0, "portLoad": 6.021, "allowedLoad": 0.000, "percentShed": 0}, {"portNumber": "2", "userID": null, "credentialID": null, "shedState": 0, "portLoad": 0.000, "allowedLoad": 0.000, "percentShed": 0}]}, {"stationID": "1:790778", "stationName": "VMWARE / HILLTOP G4", "Address": "3421 Hillview Ave, Palo Alto, California,  94304, United States", "stationLoad": 10.569, "Port": [{"portNumber": "1", "userID": "834871", "credentialID": "CNCP0000748973", "shedState": 0, "portLoad": 4.519, "allowedLoad": 0.000, "percentShed": 0}, {"portNumber": "2", "userID": "96268", "credentialID": "63f5606f4c1413", "shedState": 0, "portLoad": 6.049, "allowedLoad": 0.000, "percentShed": 0}]}, {"stationID": "1:101765", "stationName": "VMWARE / HILLTOP G5", "Address": "3421 Hillview Ave, Palo Alto, California,  94304, United States", "stationLoad": 11.666, "Port": [{"portNumber": "1", "userID": "10181", "credentialID": "8d5941e665c0e9", "shedState": 0, "portLoad": 5.727, "allowedLoad": 0.000, "percentShed": 0}, {"portNumber": "2", "userID": "80542", "credentialID": "e778ee763af38d", "shedState": 0, "portLoad": 5.939, "allowedLoad": 0.000, "percentShed": 0}]}, {"stationID": "1:594038", "stationName": "VMWARE / HILLTOP G1", "Address": "3421 Hillview Ave, Palo Alto, California,  94304, United States", "stationLoad": 0.000, "Port": [{"portNumber": "1", "userID": null, "credentialID": null, "shedState": 0, "portLoad": 0.000, "allowedLoad": 0.000, "percentShed": 0}]}, {"stationID": "1:461911", "stationName": "VMWARE / HILLTOP G2", "Address": "3421 Hillview Ave, Palo Alto, California,  94304, United States", "stationLoad": 11.574, "Port": [{"portNumber": "1", "userID": "91670", "credentialID": "43910817e0d5a3", "shedState": 0, "portLoad": 5.849, "allowedLoad": 0.000, "percentShed": 0}, {"portNumber": "2", "userID": "47708", "credentialID": "f5e61f45cd313f", "shedState": 0, "portLoad": 5.725, "allowedLoad": 0.000, "percentShed": 0}]}]}},{"ts": 1583770019.36019, "data": {"responseCode": "100", "responseText": "API input request executed successfully.", "sgID": 238421, "numStations": 5, "groupName": "Hilltop G GW", "sgLoad": "35.336", "stationData": [{"stationID": "1:195172", "stationName": "VMWARE / HILLTOP G3", "Address": "3421 Hillview Ave, Palo Alto, California,  94304, United States", "stationLoad": 6.021, "Port": [{"portNumber": "1", "userID": "58302", "credentialID": "bcf2194d8e9116", "shedState": 0, "portLoad": 6.021, "allowedLoad": 0.000, "percentShed": 0}, {"portNumber": "2", "userID": null, "credentialID": null, "shedState": 0, "portLoad": 0.000, "allowedLoad": 0.000, "percentShed": 0}]}, {"stationID": "1:790778", "stationName": "VMWARE / HILLTOP G4", "Address": "3421 Hillview Ave, Palo Alto, California,  94304, United States", "stationLoad": 6.075, "Port": [{"portNumber": "1", "userID": "834871", "credentialID": "CNCP0000748973", "shedState": 0, "portLoad": 0.000, "allowedLoad": 0.000, "percentShed": 0}, {"portNumber": "2", "userID": "96268", "credentialID": "63f5606f4c1413", "shedState": 0, "portLoad": 6.075, "allowedLoad": 0.000, "percentShed": 0}]}, {"stationID": "1:101765", "stationName": "VMWARE / HILLTOP G5", "Address": "3421 Hillview Ave, Palo Alto, California,  94304, United States", "stationLoad": 11.666, "Port": [{"portNumber": "1", "userID": "10181", "credentialID": "8d5941e665c0e9", "shedState": 0, "portLoad": 5.727, "allowedLoad": 0.000, "percentShed": 0}, {"portNumber": "2", "userID": "80542", "credentialID": "e778ee763af38d", "shedState": 0, "portLoad": 5.939, "allowedLoad": 0.000, "percentShed": 0}]}, {"stationID": "1:594038", "stationName": "VMWARE / HILLTOP G1", "Address": "3421 Hillview Ave, Palo Alto, California,  94304, United States", "stationLoad": 0.000, "Port": [{"portNumber": "1", "userID": null, "credentialID": null, "shedState": 0, "portLoad": 0.000, "allowedLoad": 0.000, "percentShed": 0}]}, {"stationID": "1:461911", "stationName": "VMWARE / HILLTOP G2", "Address": "3421 Hillview Ave, Palo Alto, California,  94304, United States", "stationLoad": 11.574, "Port": [{"portNumber": "1", "userID": "91670", "credentialID": "43910817e0d5a3", "shedState": 0, "portLoad": 5.849, "allowedLoad": 0.000, "percentShed": 0}, {"portNumber": "2", "userID": "47708", "credentialID": "f5e61f45cd313f", "shedState": 0, "portLoad": 5.725, "allowedLoad": 0.000, "percentShed": 0}]}]}},{"ts": 1583770139.5779958, "data": {"responseCode": "100", "responseText": "API input request executed successfully.", "sgID": 238421, "numStations": 5, "groupName": "Hilltop G GW", "sgLoad": "35.345", "stationData": [{"stationID": "1:195172", "stationName": "VMWARE / HILLTOP G3", "Address": "3421 Hillview Ave, Palo Alto, California,  94304, United States", "stationLoad": 6.014, "Port": [{"portNumber": "1", "userID": "58302", "credentialID": "bcf2194d8e9116", "shedState": 0, "portLoad": 6.014, "allowedLoad": 0.000, "percentShed": 0}, {"portNumber": "2", "userID": null, "credentialID": null, "shedState": 0, "portLoad": 0.000, "allowedLoad": 0.000, "percentShed": 0}]}, {"stationID": "1:790778", "stationName": "VMWARE / HILLTOP G4", "Address": "3421 Hillview Ave, Palo Alto, California,  94304, United States", "stationLoad": 6.075, "Port": [{"portNumber": "1", "userID": null, "credentialID": null, "shedState": 0, "portLoad": 0.000, "allowedLoad": 0.000, "percentShed": 0}, {"portNumber": "2", "userID": "96268", "credentialID": "63f5606f4c1413", "shedState": 0, "portLoad": 6.075, "allowedLoad": 0.000, "percentShed": 0}]}, {"stationID": "1:101765", "stationName": "VMWARE / HILLTOP G5", "Address": "3421 Hillview Ave, Palo Alto, California,  94304, United States", "stationLoad": 11.666, "Port": [{"portNumber": "1", "userID": "10181", "credentialID": "8d5941e665c0e9", "shedState": 0, "portLoad": 5.727, "allowedLoad": 0.000, "percentShed": 0}, {"portNumber": "2", "userID": "80542", "credentialID": "e778ee763af38d", "shedState": 0, "portLoad": 5.939, "allowedLoad": 0.000, "percentShed": 0}]}, {"stationID": "1:594038", "stationName": "VMWARE / HILLTOP G1", "Address": "3421 Hillview Ave, Palo Alto, California,  94304, United States", "stationLoad": 0.000, "Port": [{"portNumber": "1", "userID": null, "credentialID": null, "shedState": 0, "portLoad": 0.000, "allowedLoad": 0.000, "percentShed": 0}]}, {"stationID": "1:461911", "stationName": "VMWARE / HILLTOP G2", "Address": "3421 Hillview Ave, Palo Alto, California,  94304, United States", "stationLoad": 11.590, "Port": [{"portNumber": "1", "userID": "91670", "credentialID": "43910817e0d5a3", "shedState": 0, "portLoad": 5.849, "allowedLoad": 0.000, "percentShed": 0}, {"portNumber": "2", "userID": "47708", "credentialID": "f5e61f45cd313f", "shedState": 0, "portLoad": 5.740, "allowedLoad": 0.000, "percentShed": 0}]}]}},{"ts": 1583770259.7942162, "data": {"responseCode": "100", "responseText": "API input request executed successfully.", "sgID": 238421, "numStations": 5, "groupName": "Hilltop G GW", "sgLoad": "35.327", "stationData": [{"stationID": "1:195172", "stationName": "VMWARE / HILLTOP G3", "Address": "3421 Hillview Ave, Palo Alto, California,  94304, United States", "stationLoad": 6.014, "Port": [{"portNumber": "1", "userID": "58302", "credentialID": "bcf2194d8e9116", "shedState": 0, "portLoad": 6.014, "allowedLoad": 0.000, "percentShed": 0}, {"portNumber": "2", "userID": null, "credentialID": null, "shedState": 0, "portLoad": 0.000, "allowedLoad": 0.000, "percentShed": 0}]}, {"stationID": "1:790778", "stationName": "VMWARE / HILLTOP G4", "Address": "3421 Hillview Ave, Palo Alto, California,  94304, United States", "stationLoad": 6.075, "Port": [{"portNumber": "1", "userID": null, "credentialID": null, "shedState": 0, "portLoad": 0.000, "allowedLoad": 0.000, "percentShed": 0}, {"portNumber": "2", "userID": "96268", "credentialID": "63f5606f4c1413", "shedState": 0, "portLoad": 6.075, "allowedLoad": 0.000, "percentShed": 0}]}, {"stationID": "1:101765", "stationName": "VMWARE / HILLTOP G5", "Address": "3421 Hillview Ave, Palo Alto, California,  94304, United States", "stationLoad": 11.629, "Port": [{"portNumber": "1", "userID": "10181", "credentialID": "8d5941e665c0e9", "shedState": 0, "portLoad": 5.723, "allowedLoad": 0.000, "percentShed": 0}, {"portNumber": "2", "userID": "80542", "credentialID": "e778ee763af38d", "shedState": 0, "portLoad": 5.906, "allowedLoad": 0.000, "percentShed": 0}]}, {"stationID": "1:594038", "stationName": "VMWARE / HILLTOP G1", "Address": "3421 Hillview Ave, Palo Alto, California,  94304, United States", "stationLoad": 0.000, "Port": [{"portNumber": "1", "userID": null, "credentialID": null, "shedState": 0, "portLoad": 0.000, "allowedLoad": 0.000, "percentShed": 0}]}, {"stationID": "1:461911", "stationName": "VMWARE / HILLTOP G2", "Address": "3421 Hillview Ave, Palo Alto, California,  94304, United States", "stationLoad": 11.608, "Port": [{"portNumber": "1", "userID": "91670", "credentialID": "43910817e0d5a3", "shedState": 0, "portLoad": 5.868, "allowedLoad": 0.000, "percentShed": 0}, {"portNumber": "2", "userID": "47708", "credentialID": "f5e61f45cd313f", "shedState": 0, "portLoad": 5.740, "allowedLoad": 0.000, "percentShed": 0}]}]}},{"ts": 1583770380.0159333, "data": {"responseCode": "100", "responseText": "API input request executed successfully.", "sgID": 238421, "numStations": 5, "groupName": "Hilltop G GW", "sgLoad": "35.326", "stationData": [{"stationID": "1:195172", "stationName": "VMWARE / HILLTOP G3", "Address": "3421 Hillview Ave, Palo Alto, California,  94304, United States", "stationLoad": 6.014, "Port": [{"portNumber": "1", "userID": "58302", "credentialID": "bcf2194d8e9116", "shedState": 0, "portLoad": 6.014, "allowedLoad": 0.000, "percentShed": 0}, {"portNumber": "2", "userID": null, "credentialID": null, "shedState": 0, "portLoad": 0.000, "allowedLoad": 0.000, "percentShed": 0}]}, {"stationID": "1:790778", "stationName": "VMWARE / HILLTOP G4", "Address": "3421 Hillview Ave, Palo Alto, California,  94304, United States", "stationLoad": 6.074, "Port": [{"portNumber": "1", "userID": null, "credentialID": null, "shedState": 0, "portLoad": 0.000, "allowedLoad": 0.000, "percentShed": 0}, {"portNumber": "2", "userID": "96268", "credentialID": "63f5606f4c1413", "shedState": 0, "portLoad": 6.074, "allowedLoad": 0.000, "percentShed": 0}]}, {"stationID": "1:101765", "stationName": "VMWARE / HILLTOP G5", "Address": "3421 Hillview Ave, Palo Alto, California,  94304, United States", "stationLoad": 11.629, "Port": [{"portNumber": "1", "userID": "10181", "credentialID": "8d5941e665c0e9", "shedState": 0, "portLoad": 5.723, "allowedLoad": 0.000, "percentShed": 0}, {"portNumber": "2", "userID": "80542", "credentialID": "e778ee763af38d", "shedState": 0, "portLoad": 5.906, "allowedLoad": 0.000, "percentShed": 0}]}, {"stationID": "1:594038", "stationName": "VMWARE / HILLTOP G1", "Address": "3421 Hillview Ave, Palo Alto, California,  94304, United States", "stationLoad": 0.000, "Port": [{"portNumber": "1", "userID": null, "credentialID": null, "shedState": 0, "portLoad": 0.000, "allowedLoad": 0.000, "percentShed": 0}]}, {"stationID": "1:461911", "stationName": "VMWARE / HILLTOP G2", "Address": "3421 Hillview Ave, Palo Alto, California,  94304, United States", "stationLoad": 11.608, "Port": [{"portNumber": "1", "userID": "91670", "credentialID": "43910817e0d5a3", "shedState": 0, "portLoad": 5.868, "allowedLoad": 0.000, "percentShed": 0}, {"portNumber": "2", "userID": "47708", "credentialID": "f5e61f45cd313f", "shedState": 0, "portLoad": 5.740, "allowedLoad": 0.000, "percentShed": 0}]}]}},{"ts": 1583770500.527675, "data": {"responseCode": "100", "responseText": "API input request executed successfully.", "sgID": 238421, "numStations": 5, "groupName": "Hilltop G GW", "sgLoad": "35.321", "stationData": [{"stationID": "1:195172", "stationName": "VMWARE / HILLTOP G3", "Address": "3421 Hillview Ave, Palo Alto, California,  94304, United States", "stationLoad": 6.012, "Port": [{"portNumber": "1", "userID": "58302", "credentialID": "bcf2194d8e9116", "shedState": 0, "portLoad": 6.012, "allowedLoad": 0.000, "percentShed": 0}, {"portNumber": "2", "userID": null, "credentialID": null, "shedState": 0, "portLoad": 0.000, "allowedLoad": 0.000, "percentShed": 0}]}, {"stationID": "1:790778", "stationName": "VMWARE / HILLTOP G4", "Address": "3421 Hillview Ave, Palo Alto, California,  94304, United States", "stationLoad": 6.074, "Port": [{"portNumber": "1", "userID": null, "credentialID": null, "shedState": 0, "portLoad": 0.000, "allowedLoad": 0.000, "percentShed": 0}, {"portNumber": "2", "userID": "96268", "credentialID": "63f5606f4c1413", "shedState": 0, "portLoad": 6.074, "allowedLoad": 0.000, "percentShed": 0}]}, {"stationID": "1:101765", "stationName": "VMWARE / HILLTOP G5", "Address": "3421 Hillview Ave, Palo Alto, California,  94304, United States", "stationLoad": 11.654, "Port": [{"portNumber": "1", "userID": "10181", "credentialID": "8d5941e665c0e9", "shedState": 0, "portLoad": 5.721, "allowedLoad": 0.000, "percentShed": 0}, {"portNumber": "2", "userID": "80542", "credentialID": "e778ee763af38d", "shedState": 0, "portLoad": 5.933, "allowedLoad": 0.000, "percentShed": 0}]}, {"stationID": "1:594038", "stationName": "VMWARE / HILLTOP G1", "Address": "3421 Hillview Ave, Palo Alto, California,  94304, United States", "stationLoad": 0.000, "Port": [{"portNumber": "1", "userID": null, "credentialID": null, "shedState": 0, "portLoad": 0.000, "allowedLoad": 0.000, "percentShed": 0}]}, {"stationID": "1:461911", "stationName": "VMWARE / HILLTOP G2", "Address": "3421 Hillview Ave, Palo Alto, California,  94304, United States", "stationLoad": 11.581, "Port": [{"portNumber": "1", "userID": "91670", "credentialID": "43910817e0d5a3", "shedState": 0, "portLoad": 5.845, "allowedLoad": 0.000, "percentShed": 0}, {"portNumber": "2", "userID": "47708", "credentialID": "f5e61f45cd313f", "shedState": 0, "portLoad": 5.736, "allowedLoad": 0.000, "percentShed": 0}]}]}},{"ts": 1583770620.762315, "data": {"responseCode": "100", "responseText": "API input request executed successfully.", "sgID": 238421, "numStations": 5, "groupName": "Hilltop G GW", "sgLoad": "35.322", "stationData": [{"stationID": "1:195172", "stationName": "VMWARE / HILLTOP G3", "Address": "3421 Hillview Ave, Palo Alto, California,  94304, United States", "stationLoad": 6.012, "Port": [{"portNumber": "1", "userID": "58302", "credentialID": "bcf2194d8e9116", "shedState": 0, "portLoad": 6.012, "allowedLoad": 0.000, "percentShed": 0}, {"portNumber": "2", "userID": null, "credentialID": null, "shedState": 0, "portLoad": 0.000, "allowedLoad": 0.000, "percentShed": 0}]}, {"stationID": "1:790778", "stationName": "VMWARE / HILLTOP G4", "Address": "3421 Hillview Ave, Palo Alto, California,  94304, United States", "stationLoad": 6.075, "Port": [{"portNumber": "1", "userID": null, "credentialID": null, "shedState": 0, "portLoad": 0.000, "allowedLoad": 0.000, "percentShed": 0}, {"portNumber": "2", "userID": "96268", "credentialID": "63f5606f4c1413", "shedState": 0, "portLoad": 6.075, "allowedLoad": 0.000, "percentShed": 0}]}, {"stationID": "1:101765", "stationName": "VMWARE / HILLTOP G5", "Address": "3421 Hillview Ave, Palo Alto, California,  94304, United States", "stationLoad": 11.654, "Port": [{"portNumber": "1", "userID": "10181", "credentialID": "8d5941e665c0e9", "shedState": 0, "portLoad": 5.721, "allowedLoad": 0.000, "percentShed": 0}, {"portNumber": "2", "userID": "80542", "credentialID": "e778ee763af38d", "shedState": 0, "portLoad": 5.933, "allowedLoad": 0.000, "percentShed": 0}]}, {"stationID": "1:594038", "stationName": "VMWARE / HILLTOP G1", "Address": "3421 Hillview Ave, Palo Alto, California,  94304, United States", "stationLoad": 0.000, "Port": [{"portNumber": "1", "userID": null, "credentialID": null, "shedState": 0, "portLoad": 0.000, "allowedLoad": 0.000, "percentShed": 0}]}, {"stationID": "1:461911", "stationName": "VMWARE / HILLTOP G2", "Address": "3421 Hillview Ave, Palo Alto, California,  94304, United States", "stationLoad": 11.581, "Port": [{"portNumber": "1", "userID": "91670", "credentialID": "43910817e0d5a3", "shedState": 0, "portLoad": 5.845, "allowedLoad": 0.000, "percentShed": 0}, {"portNumber": "2", "userID": "47708", "credentialID": "f5e61f45cd313f", "shedState": 0, "portLoad": 5.736, "allowedLoad": 0.000, "percentShed": 0}]}]}},{"ts": 1583770740.994237, "data": {"responseCode": "100", "responseText": "API input request executed successfully.", "sgID": 238421, "numStations": 5, "groupName": "Hilltop G GW", "sgLoad": "38.657", "stationData": [{"stationID": "1:195172", "stationName": "VMWARE / HILLTOP G3", "Address": "3421 Hillview Ave, Palo Alto, California,  94304, United States", "stationLoad": 6.040, "Port": [{"portNumber": "1", "userID": "58302", "credentialID": "bcf2194d8e9116", "shedState": 0, "portLoad": 6.040, "allowedLoad": 0.000, "percentShed": 0}, {"portNumber": "2", "userID": null, "credentialID": null, "shedState": 0, "portLoad": 0.000, "allowedLoad": 0.000, "percentShed": 0}]}, {"stationID": "1:790778", "stationName": "VMWARE / HILLTOP G4", "Address": "3421 Hillview Ave, Palo Alto, California,  94304, United States", "stationLoad": 9.350, "Port": [{"portNumber": "1", "userID": "20476391", "credentialID": "HNA8938470603080", "shedState": 0, "portLoad": 3.276, "allowedLoad": 0.000, "percentShed": 0}, {"portNumber": "2", "userID": "96268", "credentialID": "63f5606f4c1413", "shedState": 0, "portLoad": 6.075, "allowedLoad": 0.000, "percentShed": 0}]}, {"stationID": "1:101765", "stationName": "VMWARE / HILLTOP G5", "Address": "3421 Hillview Ave, Palo Alto, California,  94304, United States", "stationLoad": 11.654, "Port": [{"portNumber": "1", "userID": "10181", "credentialID": "8d5941e665c0e9", "shedState": 0, "portLoad": 5.721, "allowedLoad": 0.000, "percentShed": 0}, {"portNumber": "2", "userID": "80542", "credentialID": "e778ee763af38d", "shedState": 0, "portLoad": 5.933, "allowedLoad": 0.000, "percentShed": 0}]}, {"stationID": "1:594038", "stationName": "VMWARE / HILLTOP G1", "Address": "3421 Hillview Ave, Palo Alto, California,  94304, United States", "stationLoad": 0.000, "Port": [{"portNumber": "1", "userID": null, "credentialID": null, "shedState": 0, "portLoad": 0.000, "allowedLoad": 0.000, "percentShed": 0}]}, {"stationID": "1:461911", "stationName": "VMWARE / HILLTOP G2", "Address": "3421 Hillview Ave, Palo Alto, California,  94304, United States", "stationLoad": 11.613, "Port": [{"portNumber": "1", "userID": "91670", "credentialID": "43910817e0d5a3", "shedState": 0, "portLoad": 5.881, "allowedLoad": 0.000, "percentShed": 0}, {"portNumber": "2", "userID": "47708", "credentialID": "f5e61f45cd313f", "shedState": 0, "portLoad": 5.732, "allowedLoad": 0.000, "percentShed": 0}]}]}},{"ts": 1583770861.244594, "data": {"responseCode": "100", "responseText": "API input request executed successfully.", "sgID": 238421, "numStations": 5, "groupName": "Hilltop G GW", "sgLoad": "38.649", "stationData": [{"stationID": "1:195172", "stationName": "VMWARE / HILLTOP G3", "Address": "3421 Hillview Ave, Palo Alto, California,  94304, United States", "stationLoad": 6.040, "Port": [{"portNumber": "1", "userID": "58302", "credentialID": "bcf2194d8e9116", "shedState": 0, "portLoad": 6.040, "allowedLoad": 0.000, "percentShed": 0}, {"portNumber": "2", "userID": null, "credentialID": null, "shedState": 0, "portLoad": 0.000, "allowedLoad": 0.000, "percentShed": 0}]}, {"stationID": "1:790778", "stationName": "VMWARE / HILLTOP G4", "Address": "3421 Hillview Ave, Palo Alto, California,  94304, United States", "stationLoad": 9.350, "Port": [{"portNumber": "1", "userID": "20476391", "credentialID": "HNA8938470603080", "shedState": 0, "portLoad": 3.276, "allowedLoad": 0.000, "percentShed": 0}, {"portNumber": "2", "userID": "96268", "credentialID": "63f5606f4c1413", "shedState": 0, "portLoad": 6.075, "allowedLoad": 0.000, "percentShed": 0}]}, {"stationID": "1:101765", "stationName": "VMWARE / HILLTOP G5", "Address": "3421 Hillview Ave, Palo Alto, California,  94304, United States", "stationLoad": 11.646, "Port": [{"portNumber": "1", "userID": "10181", "credentialID": "8d5941e665c0e9", "shedState": 0, "portLoad": 5.732, "allowedLoad": 0.000, "percentShed": 0}, {"portNumber": "2", "userID": "80542", "credentialID": "e778ee763af38d", "shedState": 0, "portLoad": 5.913, "allowedLoad": 0.000, "percentShed": 0}]}, {"stationID": "1:594038", "stationName": "VMWARE / HILLTOP G1", "Address": "3421 Hillview Ave, Palo Alto, California,  94304, United States", "stationLoad": 0.000, "Port": [{"portNumber": "1", "userID": null, "credentialID": null, "shedState": 0, "portLoad": 0.000, "allowedLoad": 0.000, "percentShed": 0}]}, {"stationID": "1:461911", "stationName": "VMWARE / HILLTOP G2", "Address": "3421 Hillview Ave, Palo Alto, California,  94304, United States", "stationLoad": 11.613, "Port": [{"portNumber": "1", "userID": "91670", "credentialID": "43910817e0d5a3", "shedState": 0, "portLoad": 5.881, "allowedLoad": 0.000, "percentShed": 0}, {"portNumber": "2", "userID": "47708", "credentialID": "f5e61f45cd313f", "shedState": 0, "portLoad": 5.732, "allowedLoad": 0.000, "percentShed": 0}]}]}},{"ts": 1583770981.5065591, "data": {"responseCode": "100", "responseText": "API input request executed successfully.", "sgID": 238421, "numStations": 5, "groupName": "Hilltop G GW", "sgLoad": "41.836", "stationData": [{"stationID": "1:195172", "stationName": "VMWARE / HILLTOP G3", "Address": "3421 Hillview Ave, Palo Alto, California,  94304, United States", "stationLoad": 9.228, "Port": [{"portNumber": "1", "userID": "58302", "credentialID": "bcf2194d8e9116", "shedState": 0, "portLoad": 6.040, "allowedLoad": 0.000, "percentShed": 0}, {"portNumber": "2", "userID": "71818", "credentialID": "5418427cbbcfcf", "shedState": 0, "portLoad": 3.188, "allowedLoad": 0.000, "percentShed": 0}]}, {"stationID": "1:790778", "stationName": "VMWARE / HILLTOP G4", "Address": "3421 Hillview Ave, Palo Alto, California,  94304, United States", "stationLoad": 9.349, "Port": [{"portNumber": "1", "userID": "20476391", "credentialID": "HNA8938470603080", "shedState": 0, "portLoad": 3.280, "allowedLoad": 0.000, "percentShed": 0}, {"portNumber": "2", "userID": "96268", "credentialID": "63f5606f4c1413", "shedState": 0, "portLoad": 6.069, "allowedLoad": 0.000, "percentShed": 0}]}, {"stationID": "1:101765", "stationName": "VMWARE / HILLTOP G5", "Address": "3421 Hillview Ave, Palo Alto, California,  94304, United States", "stationLoad": 11.646, "Port": [{"portNumber": "1", "userID": "10181", "credentialID": "8d5941e665c0e9", "shedState": 0, "portLoad": 5.732, "allowedLoad": 0.000, "percentShed": 0}, {"portNumber": "2", "userID": "80542", "credentialID": "e778ee763af38d", "shedState": 0, "portLoad": 5.913, "allowedLoad": 0.000, "percentShed": 0}]}, {"stationID": "1:594038", "stationName": "VMWARE / HILLTOP G1", "Address": "3421 Hillview Ave, Palo Alto, California,  94304, United States", "stationLoad": 0.000, "Port": [{"portNumber": "1", "userID": null, "credentialID": null, "shedState": 0, "portLoad": 0.000, "allowedLoad": 0.000, "percentShed": 0}]}, {"stationID": "1:461911", "stationName": "VMWARE / HILLTOP G2", "Address": "3421 Hillview Ave, Palo Alto, California,  94304, United States", "stationLoad": 11.613, "Port": [{"portNumber": "1", "userID": "91670", "credentialID": "43910817e0d5a3", "shedState": 0, "portLoad": 5.881, "allowedLoad": 0.000, "percentShed": 0}, {"portNumber": "2", "userID": "47708", "credentialID": "f5e61f45cd313f", "shedState": 0, "portLoad": 5.732, "allowedLoad": 0.000, "percentShed": 0}]}]}},{"ts": 1583771101.7776709, "data": {"responseCode": "100", "responseText": "API input request executed successfully.", "sgID": 238421, "numStations": 5, "groupName": "Hilltop G GW", "sgLoad": "41.730", "stationData": [{"stationID": "1:195172", "stationName": "VMWARE / HILLTOP G3", "Address": "3421 Hillview Ave, Palo Alto, California,  94304, United States", "stationLoad": 9.217, "Port": [{"portNumber": "1", "userID": "58302", "credentialID": "bcf2194d8e9116", "shedState": 0, "portLoad": 6.024, "allowedLoad": 0.000, "percentShed": 0}, {"portNumber": "2", "userID": "71818", "credentialID": "5418427cbbcfcf", "shedState": 0, "portLoad": 3.193, "allowedLoad": 0.000, "percentShed": 0}]}, {"stationID": "1:790778", "stationName": "VMWARE / HILLTOP G4", "Address": "3421 Hillview Ave, Palo Alto, California,  94304, United States", "stationLoad": 9.349, "Port": [{"portNumber": "1", "userID": "20476391", "credentialID": "HNA8938470603080", "shedState": 0, "portLoad": 3.280, "allowedLoad": 0.000, "percentShed": 0}, {"portNumber": "2", "userID": "96268", "credentialID": "63f5606f4c1413", "shedState": 0, "portLoad": 6.069, "allowedLoad": 0.000, "percentShed": 0}]}, {"stationID": "1:101765", "stationName": "VMWARE / HILLTOP G5", "Address": "3421 Hillview Ave, Palo Alto, California,  94304, United States", "stationLoad": 11.595, "Port": [{"portNumber": "1", "userID": "10181", "credentialID": "8d5941e665c0e9", "shedState": 0, "portLoad": 5.724, "allowedLoad": 0.000, "percentShed": 0}, {"portNumber": "2", "userID": "80542", "credentialID": "e778ee763af38d", "shedState": 0, "portLoad": 5.871, "allowedLoad": 0.000, "percentShed": 0}]}, {"stationID": "1:594038", "stationName": "VMWARE / HILLTOP G1", "Address": "3421 Hillview Ave, Palo Alto, California,  94304, United States", "stationLoad": 0.000, "Port": [{"portNumber": "1", "userID": null, "credentialID": null, "shedState": 0, "portLoad": 0.000, "allowedLoad": 0.000, "percentShed": 0}]}, {"stationID": "1:461911", "stationName": "VMWARE / HILLTOP G2", "Address": "3421 Hillview Ave, Palo Alto, California,  94304, United States", "stationLoad": 11.570, "Port": [{"portNumber": "1", "userID": "91670", "credentialID": "43910817e0d5a3", "shedState": 0, "portLoad": 5.849, "allowedLoad": 0.000, "percentShed": 0}, {"portNumber": "2", "userID": "47708", "credentialID": "f5e61f45cd313f", "shedState": 0, "portLoad": 5.720, "allowedLoad": 0.000, "percentShed": 0}]}]}},{"ts": 1583771222.111984, "data": {"responseCode": "100", "responseText": "API input request executed successfully.", "sgID": 238421, "numStations": 5, "groupName": "Hilltop G GW", "sgLoad": "41.678", "stationData": [{"stationID": "1:195172", "stationName": "VMWARE / HILLTOP G3", "Address": "3421 Hillview Ave, Palo Alto, California,  94304, United States", "stationLoad": 9.195, "Port": [{"portNumber": "1", "userID": "58302", "credentialID": "bcf2194d8e9116", "shedState": 0, "portLoad": 6.024, "allowedLoad": 0.000, "percentShed": 0}, {"portNumber": "2", "userID": "71818", "credentialID": "5418427cbbcfcf", "shedState": 0, "portLoad": 3.171, "allowedLoad": 0.000, "percentShed": 0}]}, {"stationID": "1:790778", "stationName": "VMWARE / HILLTOP G4", "Address": "3421 Hillview Ave, Palo Alto, California,  94304, United States", "stationLoad": 9.319, "Port": [{"portNumber": "1", "userID": "20476391", "credentialID": "HNA8938470603080", "shedState": 0, "portLoad": 3.280, "allowedLoad": 0.000, "percentShed": 0}, {"portNumber": "2", "userID": "96268", "credentialID": "63f5606f4c1413", "shedState": 0, "portLoad": 6.039, "allowedLoad": 0.000, "percentShed": 0}]}, {"stationID": "1:101765", "stationName": "VMWARE / HILLTOP G5", "Address": "3421 Hillview Ave, Palo Alto, California,  94304, United States", "stationLoad": 11.595, "Port": [{"portNumber": "1", "userID": "10181", "credentialID": "8d5941e665c0e9", "shedState": 0, "portLoad": 5.724, "allowedLoad": 0.000, "percentShed": 0}, {"portNumber": "2", "userID": "80542", "credentialID": "e778ee763af38d", "shedState": 0, "portLoad": 5.871, "allowedLoad": 0.000, "percentShed": 0}]}, {"stationID": "1:594038", "stationName": "VMWARE / HILLTOP G1", "Address": "3421 Hillview Ave, Palo Alto, California,  94304, United States", "stationLoad": 0.000, "Port": [{"portNumber": "1", "userID": null, "credentialID": null, "shedState": 0, "portLoad": 0.000, "allowedLoad": 0.000, "percentShed": 0}]}, {"stationID": "1:461911", "stationName": "VMWARE / HILLTOP G2", "Address": "3421 Hillview Ave, Palo Alto, California,  94304, United States", "stationLoad": 11.570, "Port": [{"portNumber": "1", "userID": "91670", "credentialID": "43910817e0d5a3", "shedState": 0, "portLoad": 5.849, "allowedLoad": 0.000, "percentShed": 0}, {"portNumber": "2", "userID": "47708", "credentialID": "f5e61f45cd313f", "shedState": 0, "portLoad": 5.720, "allowedLoad": 0.000, "percentShed": 0}]}]}},{"ts": 1583771342.4989052, "data": {"responseCode": "100", "responseText": "API input request executed successfully.", "sgID": 238421, "numStations": 5, "groupName": "Hilltop G GW", "sgLoad": "41.641", "stationData": [{"stationID": "1:195172", "stationName": "VMWARE / HILLTOP G3", "Address": "3421 Hillview Ave, Palo Alto, California,  94304, United States", "stationLoad": 9.184, "Port": [{"portNumber": "1", "userID": "58302", "credentialID": "bcf2194d8e9116", "shedState": 0, "portLoad": 6.013, "allowedLoad": 0.000, "percentShed": 0}, {"portNumber": "2", "userID": "71818", "credentialID": "5418427cbbcfcf", "shedState": 0, "portLoad": 3.171, "allowedLoad": 0.000, "percentShed": 0}]}, {"stationID": "1:790778", "stationName": "VMWARE / HILLTOP G4", "Address": "3421 Hillview Ave, Palo Alto, California,  94304, United States", "stationLoad": 9.306, "Port": [{"portNumber": "1", "userID": "20476391", "credentialID": "HNA8938470603080", "shedState": 0, "portLoad": 3.267, "allowedLoad": 0.000, "percentShed": 0}, {"portNumber": "2", "userID": "96268", "credentialID": "63f5606f4c1413", "shedState": 0, "portLoad": 6.039, "allowedLoad": 0.000, "percentShed": 0}]}, {"stationID": "1:101765", "stationName": "VMWARE / HILLTOP G5", "Address": "3421 Hillview Ave, Palo Alto, California,  94304, United States", "stationLoad": 11.595, "Port": [{"portNumber": "1", "userID": "10181", "credentialID": "8d5941e665c0e9", "shedState": 0, "portLoad": 5.724, "allowedLoad": 0.000, "percentShed": 0}, {"portNumber": "2", "userID": "80542", "credentialID": "e778ee763af38d", "shedState": 0, "portLoad": 5.871, "allowedLoad": 0.000, "percentShed": 0}]}, {"stationID": "1:594038", "stationName": "VMWARE / HILLTOP G1", "Address": "3421 Hillview Ave, Palo Alto, California,  94304, United States", "stationLoad": 0.000, "Port": [{"portNumber": "1", "userID": null, "credentialID": null, "shedState": 0, "portLoad": 0.000, "allowedLoad": 0.000, "percentShed": 0}]}, {"stationID": "1:461911", "stationName": "VMWARE / HILLTOP G2", "Address": "3421 Hillview Ave, Palo Alto, California,  94304, United States", "stationLoad": 11.557, "Port": [{"portNumber": "1", "userID": "91670", "credentialID": "43910817e0d5a3", "shedState": 0, "portLoad": 5.849, "allowedLoad": 0.000, "percentShed": 0}, {"portNumber": "2", "userID": "47708", "credentialID": "f5e61f45cd313f", "shedState": 0, "portLoad": 5.707, "allowedLoad": 0.000, "percentShed": 0}]}]}},{"ts": 1583771462.7535365, "data": {"responseCode": "100", "responseText": "API input request executed successfully.", "sgID": 238421, "numStations": 5, "groupName": "Hilltop G GW", "sgLoad": "41.613", "stationData": [{"stationID": "1:195172", "stationName": "VMWARE / HILLTOP G3", "Address": "3421 Hillview Ave, Palo Alto, California,  94304, United States", "stationLoad": 9.184, "Port": [{"portNumber": "1", "userID": "58302", "credentialID": "bcf2194d8e9116", "shedState": 0, "portLoad": 6.013, "allowedLoad": 0.000, "percentShed": 0}, {"portNumber": "2", "userID": "71818", "credentialID": "5418427cbbcfcf", "shedState": 0, "portLoad": 3.171, "allowedLoad": 0.000, "percentShed": 0}]}, {"stationID": "1:790778", "stationName": "VMWARE / HILLTOP G4", "Address": "3421 Hillview Ave, Palo Alto, California,  94304, United States", "stationLoad": 9.306, "Port": [{"portNumber": "1", "userID": "20476391", "credentialID": "HNA8938470603080", "shedState": 0, "portLoad": 3.267, "allowedLoad": 0.000, "percentShed": 0}, {"portNumber": "2", "userID": "96268", "credentialID": "63f5606f4c1413", "shedState": 0, "portLoad": 6.039, "allowedLoad": 0.000, "percentShed": 0}]}, {"stationID": "1:101765", "stationName": "VMWARE / HILLTOP G5", "Address": "3421 Hillview Ave, Palo Alto, California,  94304, United States", "stationLoad": 11.596, "Port": [{"portNumber": "1", "userID": "10181", "credentialID": "8d5941e665c0e9", "shedState": 0, "portLoad": 5.721, "allowedLoad": 0.000, "percentShed": 0}, {"portNumber": "2", "userID": "80542", "credentialID": "e778ee763af38d", "shedState": 0, "portLoad": 5.875, "allowedLoad": 0.000, "percentShed": 0}]}, {"stationID": "1:594038", "stationName": "VMWARE / HILLTOP G1", "Address": "3421 Hillview Ave, Palo Alto, California,  94304, United States", "stationLoad": 0.000, "Port": [{"portNumber": "1", "userID": null, "credentialID": null, "shedState": 0, "portLoad": 0.000, "allowedLoad": 0.000, "percentShed": 0}]}, {"stationID": "1:461911", "stationName": "VMWARE / HILLTOP G2", "Address": "3421 Hillview Ave, Palo Alto, California,  94304, United States", "stationLoad": 11.527, "Port": [{"portNumber": "1", "userID": "91670", "credentialID": "43910817e0d5a3", "shedState": 0, "portLoad": 5.820, "allowedLoad": 0.000, "percentShed": 0}, {"portNumber": "2", "userID": "47708", "credentialID": "f5e61f45cd313f", "shedState": 0, "portLoad": 5.707, "allowedLoad": 0.000, "percentShed": 0}]}]}},{"ts": 1583771583.0005207, "data": {"responseCode": "100", "responseText": "API input request executed successfully.", "sgID": 238421, "numStations": 5, "groupName": "Hilltop G GW", "sgLoad": "41.627", "stationData": [{"stationID": "1:195172", "stationName": "VMWARE / HILLTOP G3", "Address": "3421 Hillview Ave, Palo Alto, California,  94304, United States", "stationLoad": 9.200, "Port": [{"portNumber": "1", "userID": "58302", "credentialID": "bcf2194d8e9116", "shedState": 0, "portLoad": 6.013, "allowedLoad": 0.000, "percentShed": 0}, {"portNumber": "2", "userID": "71818", "credentialID": "5418427cbbcfcf", "shedState": 0, "portLoad": 3.187, "allowedLoad": 0.000, "percentShed": 0}]}, {"stationID": "1:790778", "stationName": "VMWARE / HILLTOP G4", "Address": "3421 Hillview Ave, Palo Alto, California,  94304, United States", "stationLoad": 9.304, "Port": [{"portNumber": "1", "userID": "20476391", "credentialID": "HNA8938470603080", "shedState": 0, "portLoad": 3.272, "allowedLoad": 0.000, "percentShed": 0}, {"portNumber": "2", "userID": "96268", "credentialID": "63f5606f4c1413", "shedState": 0, "portLoad": 6.032, "allowedLoad": 0.000, "percentShed": 0}]}, {"stationID": "1:101765", "stationName": "VMWARE / HILLTOP G5", "Address": "3421 Hillview Ave, Palo Alto, California,  94304, United States", "stationLoad": 11.596, "Port": [{"portNumber": "1", "userID": "10181", "credentialID": "8d5941e665c0e9", "shedState": 0, "portLoad": 5.721, "allowedLoad": 0.000, "percentShed": 0}, {"portNumber": "2", "userID": "80542", "credentialID": "e778ee763af38d", "shedState": 0, "portLoad": 5.875, "allowedLoad": 0.000, "percentShed": 0}]}, {"stationID": "1:594038", "stationName": "VMWARE / HILLTOP G1", "Address": "3421 Hillview Ave, Palo Alto, California,  94304, United States", "stationLoad": 0.000, "Port": [{"portNumber": "1", "userID": null, "credentialID": null, "shedState": 0, "portLoad": 0.000, "allowedLoad": 0.000, "percentShed": 0}]}, {"stationID": "1:461911", "stationName": "VMWARE / HILLTOP G2", "Address": "3421 Hillview Ave, Palo Alto, California,  94304, United States", "stationLoad": 11.527, "Port": [{"portNumber": "1", "userID": "91670", "credentialID": "43910817e0d5a3", "shedState": 0, "portLoad": 5.820, "allowedLoad": 0.000, "percentShed": 0}, {"portNumber": "2", "userID": "47708", "credentialID": "f5e61f45cd313f", "shedState": 0, "portLoad": 5.707, "allowedLoad": 0.000, "percentShed": 0}]}]}},{"ts": 1583771703.30472, "data": {"responseCode": "100", "responseText": "API input request executed successfully.", "sgID": 238421, "numStations": 5, "groupName": "Hilltop G GW", "sgLoad": "41.658", "stationData": [{"stationID": "1:195172", "stationName": "VMWARE / HILLTOP G3", "Address": "3421 Hillview Ave, Palo Alto, California,  94304, United States", "stationLoad": 9.210, "Port": [{"portNumber": "1", "userID": "58302", "credentialID": "bcf2194d8e9116", "shedState": 0, "portLoad": 6.024, "allowedLoad": 0.000, "percentShed": 0}, {"portNumber": "2", "userID": "71818", "credentialID": "5418427cbbcfcf", "shedState": 0, "portLoad": 3.187, "allowedLoad": 0.000, "percentShed": 0}]}, {"stationID": "1:790778", "stationName": "VMWARE / HILLTOP G4", "Address": "3421 Hillview Ave, Palo Alto, California,  94304, United States", "stationLoad": 9.304, "Port": [{"portNumber": "1", "userID": "20476391", "credentialID": "HNA8938470603080", "shedState": 0, "portLoad": 3.272, "allowedLoad": 0.000, "percentShed": 0}, {"portNumber": "2", "userID": "96268", "credentialID": "63f5606f4c1413", "shedState": 0, "portLoad": 6.032, "allowedLoad": 0.000, "percentShed": 0}]}, {"stationID": "1:101765", "stationName": "VMWARE / HILLTOP G5", "Address": "3421 Hillview Ave, Palo Alto, California,  94304, United States", "stationLoad": 11.592, "Port": [{"portNumber": "1", "userID": "10181", "credentialID": "8d5941e665c0e9", "shedState": 0, "portLoad": 5.719, "allowedLoad": 0.000, "percentShed": 0}, {"portNumber": "2", "userID": "80542", "credentialID": "e778ee763af38d", "shedState": 0, "portLoad": 5.874, "allowedLoad": 0.000, "percentShed": 0}]}, {"stationID": "1:594038", "stationName": "VMWARE / HILLTOP G1", "Address": "3421 Hillview Ave, Palo Alto, California,  94304, United States", "stationLoad": 0.000, "Port": [{"portNumber": "1", "userID": null, "credentialID": null, "shedState": 0, "portLoad": 0.000, "allowedLoad": 0.000, "percentShed": 0}]}, {"stationID": "1:461911", "stationName": "VMWARE / HILLTOP G2", "Address": "3421 Hillview Ave, Palo Alto, California,  94304, United States", "stationLoad": 11.551, "Port": [{"portNumber": "1", "userID": "91670", "credentialID": "43910817e0d5a3", "shedState": 0, "portLoad": 5.848, "allowedLoad": 0.000, "percentShed": 0}, {"portNumber": "2", "userID": "47708", "credentialID": "f5e61f45cd313f", "shedState": 0, "portLoad": 5.703, "allowedLoad": 0.000, "percentShed": 0}]}]}},{"ts": 1583771823.5502183, "data": {"responseCode": "100", "responseText": "API input request executed successfully.", "sgID": 238421, "numStations": 5, "groupName": "Hilltop G GW", "sgLoad": "41.643", "stationData": [{"stationID": "1:195172", "stationName": "VMWARE / HILLTOP G3", "Address": "3421 Hillview Ave, Palo Alto, California,  94304, United States", "stationLoad": 9.191, "Port": [{"portNumber": "1", "userID": "58302", "credentialID": "bcf2194d8e9116", "shedState": 0, "portLoad": 6.024, "allowedLoad": 0.000, "percentShed": 0}, {"portNumber": "2", "userID": "71818", "credentialID": "5418427cbbcfcf", "shedState": 0, "portLoad": 3.167, "allowedLoad": 0.000, "percentShed": 0}]}, {"stationID": "1:790778", "stationName": "VMWARE / HILLTOP G4", "Address": "3421 Hillview Ave, Palo Alto, California,  94304, United States", "stationLoad": 9.308, "Port": [{"portNumber": "1", "userID": "20476391", "credentialID": "HNA8938470603080", "shedState": 0, "portLoad": 3.272, "allowedLoad": 0.000, "percentShed": 0}, {"portNumber": "2", "userID": "96268", "credentialID": "63f5606f4c1413", "shedState": 0, "portLoad": 6.036, "allowedLoad": 0.000, "percentShed": 0}]}, {"stationID": "1:101765", "stationName": "VMWARE / HILLTOP G5", "Address": "3421 Hillview Ave, Palo Alto, California,  94304, United States", "stationLoad": 11.592, "Port": [{"portNumber": "1", "userID": "10181", "credentialID": "8d5941e665c0e9", "shedState": 0, "portLoad": 5.719, "allowedLoad": 0.000, "percentShed": 0}, {"portNumber": "2", "userID": "80542", "credentialID": "e778ee763af38d", "shedState": 0, "portLoad": 5.874, "allowedLoad": 0.000, "percentShed": 0}]}, {"stationID": "1:594038", "stationName": "VMWARE / HILLTOP G1", "Address": "3421 Hillview Ave, Palo Alto, California,  94304, United States", "stationLoad": 0.000, "Port": [{"portNumber": "1", "userID": null, "credentialID": null, "shedState": 0, "portLoad": 0.000, "allowedLoad": 0.000, "percentShed": 0}]}, {"stationID": "1:461911", "stationName": "VMWARE / HILLTOP G2", "Address": "3421 Hillview Ave, Palo Alto, California,  94304, United States", "stationLoad": 11.551, "Port": [{"portNumber": "1", "userID": "91670", "credentialID": "43910817e0d5a3", "shedState": 0, "portLoad": 5.848, "allowedLoad": 0.000, "percentShed": 0}, {"portNumber": "2", "userID": "47708", "credentialID": "f5e61f45cd313f", "shedState": 0, "portLoad": 5.703, "allowedLoad": 0.000, "percentShed": 0}]}]}},{"ts": 1583771943.782679, "data": {"responseCode": "100", "responseText": "API input request executed successfully.", "sgID": 238421, "numStations": 5, "groupName": "Hilltop G GW", "sgLoad": "41.615", "stationData": [{"stationID": "1:195172", "stationName": "VMWARE / HILLTOP G3", "Address": "3421 Hillview Ave, Palo Alto, California,  94304, United States", "stationLoad": 9.194, "Port": [{"portNumber": "1", "userID": "58302", "credentialID": "bcf2194d8e9116", "shedState": 0, "portLoad": 6.027, "allowedLoad": 0.000, "percentShed": 0}, {"portNumber": "2", "userID": "71818", "credentialID": "5418427cbbcfcf", "shedState": 0, "portLoad": 3.167, "allowedLoad": 0.000, "percentShed": 0}]}, {"stationID": "1:790778", "stationName": "VMWARE / HILLTOP G4", "Address": "3421 Hillview Ave, Palo Alto, California,  94304, United States", "stationLoad": 9.307, "Port": [{"portNumber": "1", "userID": "20476391", "credentialID": "HNA8938470603080", "shedState": 0, "portLoad": 3.270, "allowedLoad": 0.000, "percentShed": 0}, {"portNumber": "2", "userID": "96268", "credentialID": "63f5606f4c1413", "shedState": 0, "portLoad": 6.036, "allowedLoad": 0.000, "percentShed": 0}]}, {"stationID": "1:101765", "stationName": "VMWARE / HILLTOP G5", "Address": "3421 Hillview Ave, Palo Alto, California,  94304, United States", "stationLoad": 11.592, "Port": [{"portNumber": "1", "userID": "10181", "credentialID": "8d5941e665c0e9", "shedState": 0, "portLoad": 5.719, "allowedLoad": 0.000, "percentShed": 0}, {"portNumber": "2", "userID": "80542", "credentialID": "e778ee763af38d", "shedState": 0, "portLoad": 5.874, "allowedLoad": 0.000, "percentShed": 0}]}, {"stationID": "1:594038", "stationName": "VMWARE / HILLTOP G1", "Address": "3421 Hillview Ave, Palo Alto, California,  94304, United States", "stationLoad": 0.000, "Port": [{"portNumber": "1", "userID": null, "credentialID": null, "shedState": 0, "portLoad": 0.000, "allowedLoad": 0.000, "percentShed": 0}]}, {"stationID": "1:461911", "stationName": "VMWARE / HILLTOP G2", "Address": "3421 Hillview Ave, Palo Alto, California,  94304, United States", "stationLoad": 11.522, "Port": [{"portNumber": "1", "userID": "91670", "credentialID": "43910817e0d5a3", "shedState": 0, "portLoad": 5.820, "allowedLoad": 0.000, "percentShed": 0}, {"portNumber": "2", "userID": "47708", "credentialID": "f5e61f45cd313f", "shedState": 0, "portLoad": 5.701, "allowedLoad": 0.000, "percentShed": 0}]}]}},{"ts": 1583772064.1518834, "data": {"responseCode": "100", "responseText": "API input request executed successfully.", "sgID": 238421, "numStations": 5, "groupName": "Hilltop G GW", "sgLoad": "41.610", "stationData": [{"stationID": "1:195172", "stationName": "VMWARE / HILLTOP G3", "Address": "3421 Hillview Ave, Palo Alto, California,  94304, United States", "stationLoad": 9.194, "Port": [{"portNumber": "1", "userID": "58302", "credentialID": "bcf2194d8e9116", "shedState": 0, "portLoad": 6.027, "allowedLoad": 0.000, "percentShed": 0}, {"portNumber": "2", "userID": "71818", "credentialID": "5418427cbbcfcf", "shedState": 0, "portLoad": 3.167, "allowedLoad": 0.000, "percentShed": 0}]}, {"stationID": "1:790778", "stationName": "VMWARE / HILLTOP G4", "Address": "3421 Hillview Ave, Palo Alto, California,  94304, United States", "stationLoad": 9.307, "Port": [{"portNumber": "1", "userID": "20476391", "credentialID": "HNA8938470603080", "shedState": 0, "portLoad": 3.270, "allowedLoad": 0.000, "percentShed": 0}, {"portNumber": "2", "userID": "96268", "credentialID": "63f5606f4c1413", "shedState": 0, "portLoad": 6.036, "allowedLoad": 0.000, "percentShed": 0}]}, {"stationID": "1:101765", "stationName": "VMWARE / HILLTOP G5", "Address": "3421 Hillview Ave, Palo Alto, California,  94304, United States", "stationLoad": 11.587, "Port": [{"portNumber": "1", "userID": "10181", "credentialID": "8d5941e665c0e9", "shedState": 0, "portLoad": 5.710, "allowedLoad": 0.000, "percentShed": 0}, {"portNumber": "2", "userID": "80542", "credentialID": "e778ee763af38d", "shedState": 0, "portLoad": 5.877, "allowedLoad": 0.000, "percentShed": 0}]}, {"stationID": "1:594038", "stationName": "VMWARE / HILLTOP G1", "Address": "3421 Hillview Ave, Palo Alto, California,  94304, United States", "stationLoad": 0.000, "Port": [{"portNumber": "1", "userID": null, "credentialID": null, "shedState": 0, "portLoad": 0.000, "allowedLoad": 0.000, "percentShed": 0}]}, {"stationID": "1:461911", "stationName": "VMWARE / HILLTOP G2", "Address": "3421 Hillview Ave, Palo Alto, California,  94304, United States", "stationLoad": 11.522, "Port": [{"portNumber": "1", "userID": "91670", "credentialID": "43910817e0d5a3", "shedState": 0, "portLoad": 5.820, "allowedLoad": 0.000, "percentShed": 0}, {"portNumber": "2", "userID": "47708", "credentialID": "f5e61f45cd313f", "shedState": 0, "portLoad": 5.701, "allowedLoad": 0.000, "percentShed": 0}]}]}},{"ts": 1583772184.486327, "data": {"responseCode": "100", "responseText": "API input request executed successfully.", "sgID": 238421, "numStations": 5, "groupName": "Hilltop G GW", "sgLoad": "41.624", "stationData": [{"stationID": "1:195172", "stationName": "VMWARE / HILLTOP G3", "Address": "3421 Hillview Ave, Palo Alto, California,  94304, United States", "stationLoad": 9.206, "Port": [{"portNumber": "1", "userID": "58302", "credentialID": "bcf2194d8e9116", "shedState": 0, "portLoad": 6.027, "allowedLoad": 0.000, "percentShed": 0}, {"portNumber": "2", "userID": "71818", "credentialID": "5418427cbbcfcf", "shedState": 0, "portLoad": 3.179, "allowedLoad": 0.000, "percentShed": 0}]}, {"stationID": "1:790778", "stationName": "VMWARE / HILLTOP G4", "Address": "3421 Hillview Ave, Palo Alto, California,  94304, United States", "stationLoad": 9.309, "Port": [{"portNumber": "1", "userID": "20476391", "credentialID": "HNA8938470603080", "shedState": 0, "portLoad": 3.275, "allowedLoad": 0.000, "percentShed": 0}, {"portNumber": "2", "userID": "96268", "credentialID": "63f5606f4c1413", "shedState": 0, "portLoad": 6.034, "allowedLoad": 0.000, "percentShed": 0}]}, {"stationID": "1:101765", "stationName": "VMWARE / HILLTOP G5", "Address": "3421 Hillview Ave, Palo Alto, California,  94304, United States", "stationLoad": 11.587, "Port": [{"portNumber": "1", "userID": "10181", "credentialID": "8d5941e665c0e9", "shedState": 0, "portLoad": 5.710, "allowedLoad": 0.000, "percentShed": 0}, {"portNumber": "2", "userID": "80542", "credentialID": "e778ee763af38d", "shedState": 0, "portLoad": 5.877, "allowedLoad": 0.000, "percentShed": 0}]}, {"stationID": "1:594038", "stationName": "VMWARE / HILLTOP G1", "Address": "3421 Hillview Ave, Palo Alto, California,  94304, United States", "stationLoad": 0.000, "Port": [{"portNumber": "1", "userID": null, "credentialID": null, "shedState": 0, "portLoad": 0.000, "allowedLoad": 0.000, "percentShed": 0}]}, {"stationID": "1:461911", "stationName": "VMWARE / HILLTOP G2", "Address": "3421 Hillview Ave, Palo Alto, California,  94304, United States", "stationLoad": 11.522, "Port": [{"portNumber": "1", "userID": "91670", "credentialID": "43910817e0d5a3", "shedState": 0, "portLoad": 5.820, "allowedLoad": 0.000, "percentShed": 0}, {"portNumber": "2", "userID": "47708", "credentialID": "f5e61f45cd313f", "shedState": 0, "portLoad": 5.701, "allowedLoad": 0.000, "percentShed": 0}]}]}},{"ts": 1583772304.7877033, "data": {"responseCode": "100", "responseText": "API input request executed successfully.", "sgID": 238421, "numStations": 5, "groupName": "Hilltop G GW", "sgLoad": "41.672", "stationData": [{"stationID": "1:195172", "stationName": "VMWARE / HILLTOP G3", "Address": "3421 Hillview Ave, Palo Alto, California,  94304, United States", "stationLoad": 9.218, "Port": [{"portNumber": "1", "userID": "58302", "credentialID": "bcf2194d8e9116", "shedState": 0, "portLoad": 6.039, "allowedLoad": 0.000, "percentShed": 0}, {"portNumber": "2", "userID": "71818", "credentialID": "5418427cbbcfcf", "shedState": 0, "portLoad": 3.179, "allowedLoad": 0.000, "percentShed": 0}]}, {"stationID": "1:790778", "stationName": "VMWARE / HILLTOP G4", "Address": "3421 Hillview Ave, Palo Alto, California,  94304, United States", "stationLoad": 9.309, "Port": [{"portNumber": "1", "userID": "20476391", "credentialID": "HNA8938470603080", "shedState": 0, "portLoad": 3.275, "allowedLoad": 0.000, "percentShed": 0}, {"portNumber": "2", "userID": "96268", "credentialID": "63f5606f4c1413", "shedState": 0, "portLoad": 6.034, "allowedLoad": 0.000, "percentShed": 0}]}, {"stationID": "1:101765", "stationName": "VMWARE / HILLTOP G5", "Address": "3421 Hillview Ave, Palo Alto, California,  94304, United States", "stationLoad": 11.595, "Port": [{"portNumber": "1", "userID": "10181", "credentialID": "8d5941e665c0e9", "shedState": 0, "portLoad": 5.718, "allowedLoad": 0.000, "percentShed": 0}, {"portNumber": "2", "userID": "80542", "credentialID": "e778ee763af38d", "shedState": 0, "portLoad": 5.878, "allowedLoad": 0.000, "percentShed": 0}]}, {"stationID": "1:594038", "stationName": "VMWARE / HILLTOP G1", "Address": "3421 Hillview Ave, Palo Alto, California,  94304, United States", "stationLoad": 0.000, "Port": [{"portNumber": "1", "userID": null, "credentialID": null, "shedState": 0, "portLoad": 0.000, "allowedLoad": 0.000, "percentShed": 0}]}, {"stationID": "1:461911", "stationName": "VMWARE / HILLTOP G2", "Address": "3421 Hillview Ave, Palo Alto, California,  94304, United States", "stationLoad": 11.549, "Port": [{"portNumber": "1", "userID": "91670", "credentialID": "43910817e0d5a3", "shedState": 0, "portLoad": 5.836, "allowedLoad": 0.000, "percentShed": 0}, {"portNumber": "2", "userID": "47708", "credentialID": "f5e61f45cd313f", "shedState": 0, "portLoad": 5.713, "allowedLoad": 0.000, "percentShed": 0}]}]}},{"ts": 1583772425.0631638, "data": {"responseCode": "100", "responseText": "API input request executed successfully.", "sgID": 238421, "numStations": 5, "groupName": "Hilltop G GW", "sgLoad": "41.668", "stationData": [{"stationID": "1:195172", "stationName": "VMWARE / HILLTOP G3", "Address": "3421 Hillview Ave, Palo Alto, California,  94304, United States", "stationLoad": 9.232, "Port": [{"portNumber": "1", "userID": "58302", "credentialID": "bcf2194d8e9116", "shedState": 0, "portLoad": 6.039, "allowedLoad": 0.000, "percentShed": 0}, {"portNumber": "2", "userID": "71818", "credentialID": "5418427cbbcfcf", "shedState": 0, "portLoad": 3.193, "allowedLoad": 0.000, "percentShed": 0}]}, {"stationID": "1:790778", "stationName": "VMWARE / HILLTOP G4", "Address": "3421 Hillview Ave, Palo Alto, California,  94304, United States", "stationLoad": 9.291, "Port": [{"portNumber": "1", "userID": "20476391", "credentialID": "HNA8938470603080", "shedState": 0, "portLoad": 3.268, "allowedLoad": 0.000, "percentShed": 0}, {"portNumber": "2", "userID": "96268", "credentialID": "63f5606f4c1413", "shedState": 0, "portLoad": 6.023, "allowedLoad": 0.000, "percentShed": 0}]}, {"stationID": "1:101765", "stationName": "VMWARE / HILLTOP G5", "Address": "3421 Hillview Ave, Palo Alto, California,  94304, United States", "stationLoad": 11.595, "Port": [{"portNumber": "1", "userID": "10181", "credentialID": "8d5941e665c0e9", "shedState": 0, "portLoad": 5.718, "allowedLoad": 0.000, "percentShed": 0}, {"portNumber": "2", "userID": "80542", "credentialID": "e778ee763af38d", "shedState": 0, "portLoad": 5.878, "allowedLoad": 0.000, "percentShed": 0}]}, {"stationID": "1:594038", "stationName": "VMWARE / HILLTOP G1", "Address": "3421 Hillview Ave, Palo Alto, California,  94304, United States", "stationLoad": 0.000, "Port": [{"portNumber": "1", "userID": null, "credentialID": null, "shedState": 0, "portLoad": 0.000, "allowedLoad": 0.000, "percentShed": 0}]}, {"stationID": "1:461911", "stationName": "VMWARE / HILLTOP G2", "Address": "3421 Hillview Ave, Palo Alto, California,  94304, United States", "stationLoad": 11.549, "Port": [{"portNumber": "1", "userID": "91670", "credentialID": "43910817e0d5a3", "shedState": 0, "portLoad": 5.836, "allowedLoad": 0.000, "percentShed": 0}, {"portNumber": "2", "userID": "47708", "credentialID": "f5e61f45cd313f", "shedState": 0, "portLoad": 5.713, "allowedLoad": 0.000, "percentShed": 0}]}]}},{"ts": 1583772545.3348494, "data": {"responseCode": "100", "responseText": "API input request executed successfully.", "sgID": 238421, "numStations": 5, "groupName": "Hilltop G GW", "sgLoad": "35.911", "stationData": [{"stationID": "1:195172", "stationName": "VMWARE / HILLTOP G3", "Address": "3421 Hillview Ave, Palo Alto, California,  94304, United States", "stationLoad": 9.205, "Port": [{"portNumber": "1", "userID": "58302", "credentialID": "bcf2194d8e9116", "shedState": 0, "portLoad": 6.012, "allowedLoad": 0.000, "percentShed": 0}, {"portNumber": "2", "userID": "71818", "credentialID": "5418427cbbcfcf", "shedState": 0, "portLoad": 3.193, "allowedLoad": 0.000, "percentShed": 0}]}, {"stationID": "1:790778", "stationName": "VMWARE / HILLTOP G4", "Address": "3421 Hillview Ave, Palo Alto, California,  94304, United States", "stationLoad": 9.291, "Port": [{"portNumber": "1", "userID": "20476391", "credentialID": "HNA8938470603080", "shedState": 0, "portLoad": 3.268, "allowedLoad": 0.000, "percentShed": 0}, {"portNumber": "2", "userID": "96268", "credentialID": "63f5606f4c1413", "shedState": 0, "portLoad": 6.023, "allowedLoad": 0.000, "percentShed": 0}]}, {"stationID": "1:101765", "stationName": "VMWARE / HILLTOP G5", "Address": "3421 Hillview Ave, Palo Alto, California,  94304, United States", "stationLoad": 11.595, "Port": [{"portNumber": "1", "userID": "10181", "credentialID": "8d5941e665c0e9", "shedState": 0, "portLoad": 5.718, "allowedLoad": 0.000, "percentShed": 0}, {"portNumber": "2", "userID": "80542", "credentialID": "e778ee763af38d", "shedState": 0, "portLoad": 5.878, "allowedLoad": 0.000, "percentShed": 0}]}, {"stationID": "1:594038", "stationName": "VMWARE / HILLTOP G1", "Address": "3421 Hillview Ave, Palo Alto, California,  94304, United States", "stationLoad": 0.000, "Port": [{"portNumber": "1", "userID": null, "credentialID": null, "shedState": 0, "portLoad": 0.000, "allowedLoad": 0.000, "percentShed": 0}]}, {"stationID": "1:461911", "stationName": "VMWARE / HILLTOP G2", "Address": "3421 Hillview Ave, Palo Alto, California,  94304, United States", "stationLoad": 5.819, "Port": [{"portNumber": "1", "userID": "91670", "credentialID": "43910817e0d5a3", "shedState": 0, "portLoad": 5.819, "allowedLoad": 0.000, "percentShed": 0}, {"portNumber": "2", "userID": "47708", "credentialID": "f5e61f45cd313f", "shedState": 0, "portLoad": 0.000, "allowedLoad": 0.000, "percentShed": 0}]}]}},{"ts": 1583772665.6156354, "data": {"responseCode": "100", "responseText": "API input request executed successfully.", "sgID": 238421, "numStations": 5, "groupName": "Hilltop G GW", "sgLoad": "35.900", "stationData": [{"stationID": "1:195172", "stationName": "VMWARE / HILLTOP G3", "Address": "3421 Hillview Ave, Palo Alto, California,  94304, United States", "stationLoad": 9.205, "Port": [{"portNumber": "1", "userID": "58302", "credentialID": "bcf2194d8e9116", "shedState": 0, "portLoad": 6.012, "allowedLoad": 0.000, "percentShed": 0}, {"portNumber": "2", "userID": "71818", "credentialID": "5418427cbbcfcf", "shedState": 0, "portLoad": 3.193, "allowedLoad": 0.000, "percentShed": 0}]}, {"stationID": "1:790778", "stationName": "VMWARE / HILLTOP G4", "Address": "3421 Hillview Ave, Palo Alto, California,  94304, United States", "stationLoad": 9.291, "Port": [{"portNumber": "1", "userID": "20476391", "credentialID": "HNA8938470603080", "shedState": 0, "portLoad": 3.268, "allowedLoad": 0.000, "percentShed": 0}, {"portNumber": "2", "userID": "96268", "credentialID": "63f5606f4c1413", "shedState": 0, "portLoad": 6.023, "allowedLoad": 0.000, "percentShed": 0}]}, {"stationID": "1:101765", "stationName": "VMWARE / HILLTOP G5", "Address": "3421 Hillview Ave, Palo Alto, California,  94304, United States", "stationLoad": 11.584, "Port": [{"portNumber": "1", "userID": "10181", "credentialID": "8d5941e665c0e9", "shedState": 0, "portLoad": 5.720, "allowedLoad": 0.000, "percentShed": 0}, {"portNumber": "2", "userID": "80542", "credentialID": "e778ee763af38d", "shedState": 0, "portLoad": 5.865, "allowedLoad": 0.000, "percentShed": 0}]}, {"stationID": "1:594038", "stationName": "VMWARE / HILLTOP G1", "Address": "3421 Hillview Ave, Palo Alto, California,  94304, United States", "stationLoad": 0.000, "Port": [{"portNumber": "1", "userID": null, "credentialID": null, "shedState": 0, "portLoad": 0.000, "allowedLoad": 0.000, "percentShed": 0}]}, {"stationID": "1:461911", "stationName": "VMWARE / HILLTOP G2", "Address": "3421 Hillview Ave, Palo Alto, California,  94304, United States", "stationLoad": 5.819, "Port": [{"portNumber": "1", "userID": "91670", "credentialID": "43910817e0d5a3", "shedState": 0, "portLoad": 5.819, "allowedLoad": 0.000, "percentShed": 0}, {"portNumber": "2", "userID": null, "credentialID": null, "shedState": 0, "portLoad": 0.000, "allowedLoad": 0.000, "percentShed": 0}]}]}},{"ts": 1583772785.8467588, "data": {"responseCode": "100", "responseText": "API input request executed successfully.", "sgID": 238421, "numStations": 5, "groupName": "Hilltop G GW", "sgLoad": "35.906", "stationData": [{"stationID": "1:195172", "stationName": "VMWARE / HILLTOP G3", "Address": "3421 Hillview Ave, Palo Alto, California,  94304, United States", "stationLoad": 9.213, "Port": [{"portNumber": "1", "userID": "58302", "credentialID": "bcf2194d8e9116", "shedState": 0, "portLoad": 6.012, "allowedLoad": 0.000, "percentShed": 0}, {"portNumber": "2", "userID": "71818", "credentialID": "5418427cbbcfcf", "shedState": 0, "portLoad": 3.201, "allowedLoad": 0.000, "percentShed": 0}]}, {"stationID": "1:790778", "stationName": "VMWARE / HILLTOP G4", "Address": "3421 Hillview Ave, Palo Alto, California,  94304, United States", "stationLoad": 9.290, "Port": [{"portNumber": "1", "userID": "20476391", "credentialID": "HNA8938470603080", "shedState": 0, "portLoad": 3.261, "allowedLoad": 0.000, "percentShed": 0}, {"portNumber": "2", "userID": "96268", "credentialID": "63f5606f4c1413", "shedState": 0, "portLoad": 6.029, "allowedLoad": 0.000, "percentShed": 0}]}, {"stationID": "1:101765", "stationName": "VMWARE / HILLTOP G5", "Address": "3421 Hillview Ave, Palo Alto, California,  94304, United States", "stationLoad": 11.584, "Port": [{"portNumber": "1", "userID": "10181", "credentialID": "8d5941e665c0e9", "shedState": 0, "portLoad": 5.720, "allowedLoad": 0.000, "percentShed": 0}, {"portNumber": "2", "userID": "80542", "credentialID": "e778ee763af38d", "shedState": 0, "portLoad": 5.865, "allowedLoad": 0.000, "percentShed": 0}]}, {"stationID": "1:594038", "stationName": "VMWARE / HILLTOP G1", "Address": "3421 Hillview Ave, Palo Alto, California,  94304, United States", "stationLoad": 0.000, "Port": [{"portNumber": "1", "userID": null, "credentialID": null, "shedState": 0, "portLoad": 0.000, "allowedLoad": 0.000, "percentShed": 0}]}, {"stationID": "1:461911", "stationName": "VMWARE / HILLTOP G2", "Address": "3421 Hillview Ave, Palo Alto, California,  94304, United States", "stationLoad": 5.819, "Port": [{"portNumber": "1", "userID": "91670", "credentialID": "43910817e0d5a3", "shedState": 0, "portLoad": 5.819, "allowedLoad": 0.000, "percentShed": 0}, {"portNumber": "2", "userID": null, "credentialID": null, "shedState": 0, "portLoad": 0.000, "allowedLoad": 0.000, "percentShed": 0}]}]}},{"ts": 1583772906.1011415, "data": {"responseCode": "100", "responseText": "API input request executed successfully.", "sgID": 238421, "numStations": 5, "groupName": "Hilltop G GW", "sgLoad": "35.943", "stationData": [{"stationID": "1:195172", "stationName": "VMWARE / HILLTOP G3", "Address": "3421 Hillview Ave, Palo Alto, California,  94304, United States", "stationLoad": 9.241, "Port": [{"portNumber": "1", "userID": "58302", "credentialID": "bcf2194d8e9116", "shedState": 0, "portLoad": 6.040, "allowedLoad": 0.000, "percentShed": 0}, {"portNumber": "2", "userID": "71818", "credentialID": "5418427cbbcfcf", "shedState": 0, "portLoad": 3.201, "allowedLoad": 0.000, "percentShed": 0}]}, {"stationID": "1:790778", "stationName": "VMWARE / HILLTOP G4", "Address": "3421 Hillview Ave, Palo Alto, California,  94304, United States", "stationLoad": 9.290, "Port": [{"portNumber": "1", "userID": "20476391", "credentialID": "HNA8938470603080", "shedState": 0, "portLoad": 3.261, "allowedLoad": 0.000, "percentShed": 0}, {"portNumber": "2", "userID": "96268", "credentialID": "63f5606f4c1413", "shedState": 0, "portLoad": 6.029, "allowedLoad": 0.000, "percentShed": 0}]}, {"stationID": "1:101765", "stationName": "VMWARE / HILLTOP G5", "Address": "3421 Hillview Ave, Palo Alto, California,  94304, United States", "stationLoad": 11.587, "Port": [{"portNumber": "1", "userID": "10181", "credentialID": "8d5941e665c0e9", "shedState": 0, "portLoad": 5.719, "allowedLoad": 0.000, "percentShed": 0}, {"portNumber": "2", "userID": "80542", "credentialID": "e778ee763af38d", "shedState": 0, "portLoad": 5.869, "allowedLoad": 0.000, "percentShed": 0}]}, {"stationID": "1:594038", "stationName": "VMWARE / HILLTOP G1", "Address": "3421 Hillview Ave, Palo Alto, California,  94304, United States", "stationLoad": 0.000, "Port": [{"portNumber": "1", "userID": null, "credentialID": null, "shedState": 0, "portLoad": 0.000, "allowedLoad": 0.000, "percentShed": 0}]}, {"stationID": "1:461911", "stationName": "VMWARE / HILLTOP G2", "Address": "3421 Hillview Ave, Palo Alto, California,  94304, United States", "stationLoad": 5.824, "Port": [{"portNumber": "1", "userID": "91670", "credentialID": "43910817e0d5a3", "shedState": 0, "portLoad": 5.824, "allowedLoad": 0.000, "percentShed": 0}, {"portNumber": "2", "userID": null, "credentialID": null, "shedState": 0, "portLoad": 0.000, "allowedLoad": 0.000, "percentShed": 0}]}]}},{"ts": 1583773026.596651, "data": {"responseCode": "100", "responseText": "API input request executed successfully.", "sgID": 238421, "numStations": 5, "groupName": "Hilltop G GW", "sgLoad": "41.810", "stationData": [{"stationID": "1:195172", "stationName": "VMWARE / HILLTOP G3", "Address": "3421 Hillview Ave, Palo Alto, California,  94304, United States", "stationLoad": 9.214, "Port": [{"portNumber": "1", "userID": "58302", "credentialID": "bcf2194d8e9116", "shedState": 0, "portLoad": 6.040, "allowedLoad": 0.000, "percentShed": 0}, {"portNumber": "2", "userID": "71818", "credentialID": "5418427cbbcfcf", "shedState": 0, "portLoad": 3.174, "allowedLoad": 0.000, "percentShed": 0}]}, {"stationID": "1:790778", "stationName": "VMWARE / HILLTOP G4", "Address": "3421 Hillview Ave, Palo Alto, California,  94304, United States", "stationLoad": 9.274, "Port": [{"portNumber": "1", "userID": "20476391", "credentialID": "HNA8938470603080", "shedState": 0, "portLoad": 3.268, "allowedLoad": 0.000, "percentShed": 0}, {"portNumber": "2", "userID": "96268", "credentialID": "63f5606f4c1413", "shedState": 0, "portLoad": 6.005, "allowedLoad": 0.000, "percentShed": 0}]}, {"stationID": "1:101765", "stationName": "VMWARE / HILLTOP G5", "Address": "3421 Hillview Ave, Palo Alto, California,  94304, United States", "stationLoad": 11.587, "Port": [{"portNumber": "1", "userID": "10181", "credentialID": "8d5941e665c0e9", "shedState": 0, "portLoad": 5.719, "allowedLoad": 0.000, "percentShed": 0}, {"portNumber": "2", "userID": "80542", "credentialID": "e778ee763af38d", "shedState": 0, "portLoad": 5.869, "allowedLoad": 0.000, "percentShed": 0}]}, {"stationID": "1:594038", "stationName": "VMWARE / HILLTOP G1", "Address": "3421 Hillview Ave, Palo Alto, California,  94304, United States", "stationLoad": 0.000, "Port": [{"portNumber": "1", "userID": null, "credentialID": null, "shedState": 0, "portLoad": 0.000, "allowedLoad": 0.000, "percentShed": 0}]}, {"stationID": "1:461911", "stationName": "VMWARE / HILLTOP G2", "Address": "3421 Hillview Ave, Palo Alto, California,  94304, United States", "stationLoad": 11.735, "Port": [{"portNumber": "1", "userID": "91670", "credentialID": "43910817e0d5a3", "shedState": 0, "portLoad": 5.824, "allowedLoad": 0.000, "percentShed": 0}, {"portNumber": "2", "userID": "28136", "credentialID": "f57d108255d6f2", "shedState": 0, "portLoad": 5.911, "allowedLoad": 0.000, "percentShed": 0}]}]}},{"ts": 1583773146.8059914, "data": {"responseCode": "100", "responseText": "API input request executed successfully.", "sgID": 238421, "numStations": 5, "groupName": "Hilltop G GW", "sgLoad": "30.071", "stationData": [{"stationID": "1:195172", "stationName": "VMWARE / HILLTOP G3", "Address": "3421 Hillview Ave, Palo Alto, California,  94304, United States", "stationLoad": 3.174, "Port": [{"portNumber": "1", "userID": "58302", "credentialID": "bcf2194d8e9116", "shedState": 0, "portLoad": 0.000, "allowedLoad": 0.000, "percentShed": 0}, {"portNumber": "2", "userID": "71818", "credentialID": "5418427cbbcfcf", "shedState": 0, "portLoad": 3.174, "allowedLoad": 0.000, "percentShed": 0}]}, {"stationID": "1:790778", "stationName": "VMWARE / HILLTOP G4", "Address": "3421 Hillview Ave, Palo Alto, California,  94304, United States", "stationLoad": 9.274, "Port": [{"portNumber": "1", "userID": "20476391", "credentialID": "HNA8938470603080", "shedState": 0, "portLoad": 3.268, "allowedLoad": 0.000, "percentShed": 0}, {"portNumber": "2", "userID": "96268", "credentialID": "63f5606f4c1413", "shedState": 0, "portLoad": 6.005, "allowedLoad": 0.000, "percentShed": 0}]}, {"stationID": "1:101765", "stationName": "VMWARE / HILLTOP G5", "Address": "3421 Hillview Ave, Palo Alto, California,  94304, United States", "stationLoad": 5.869, "Port": [{"portNumber": "1", "userID": "10181", "credentialID": "8d5941e665c0e9", "shedState": 0, "portLoad": 0.000, "allowedLoad": 0.000, "percentShed": 0}, {"portNumber": "2", "userID": "80542", "credentialID": "e778ee763af38d", "shedState": 0, "portLoad": 5.869, "allowedLoad": 0.000, "percentShed": 0}]}, {"stationID": "1:594038", "stationName": "VMWARE / HILLTOP G1", "Address": "3421 Hillview Ave, Palo Alto, California,  94304, United States", "stationLoad": 0.000, "Port": [{"portNumber": "1", "userID": null, "credentialID": null, "shedState": 0, "portLoad": 0.000, "allowedLoad": 0.000, "percentShed": 0}]}, {"stationID": "1:461911", "stationName": "VMWARE / HILLTOP G2", "Address": "3421 Hillview Ave, Palo Alto, California,  94304, United States", "stationLoad": 11.754, "Port": [{"portNumber": "1", "userID": "91670", "credentialID": "43910817e0d5a3", "shedState": 0, "portLoad": 5.846, "allowedLoad": 0.000, "percentShed": 0}, {"portNumber": "2", "userID": "28136", "credentialID": "f57d108255d6f2", "shedState": 0, "portLoad": 5.908, "allowedLoad": 0.000, "percentShed": 0}]}]}}]}
